makenew_pypackage/__init__.py
makenew_pypackage/todo.py
makenew_pypackage-5.3.0.dist-info/LICENSE.txt
makenew_pypackage-5.3.0.dist-info/METADATA
makenew_pypackage-5.3.0.dist-info/WHEEL
makenew_pypackage-5.3.0.dist-info/RECORD
