Metadata-Version: 2.1
Name: makenew-pypackage
Version: 5.3.0
Summary: Package skeleton for a Python module.
Home-page: https://github.com/makenew/pypackage
License: MIT
Author: Evan Sosenko
Author-email: razorx@evansosenko.com
Requires-Python: >=3.11.0,<4.0.0
Classifier: License :: OSI Approved :: MIT License
Classifier: Programming Language :: Python :: 3
Classifier: Programming Language :: Python :: 3.11
Classifier: Programming Language :: Python :: 3.12
Project-URL: Repository, https://github.com/makenew/pypackage
